LICENSE
MANIFEST.in
README.rst
setup.py
procinfo/__init__.py
procinfo/__init__.pyc
procinfo/patch.py
procinfo/patch.pyc
procinfo.egg-info/PKG-INFO
procinfo.egg-info/SOURCES.txt
procinfo.egg-info/dependency_links.txt
procinfo.egg-info/requires.txt
procinfo.egg-info/top_level.txt
tests/__init__.py
tests/__init__.pyc